es_query_builder/__init__.py
es_query_builder/cli.py
es_query_builder/es_query_builder.py
es_query_builder-0.2.1.dist-info/AUTHORS.rst
es_query_builder-0.2.1.dist-info/LICENSE
es_query_builder-0.2.1.dist-info/METADATA
es_query_builder-0.2.1.dist-info/WHEEL
es_query_builder-0.2.1.dist-info/entry_points.txt
es_query_builder-0.2.1.dist-info/top_level.txt
es_query_builder-0.2.1.dist-info/RECORD
