Metadata-Version: 2.1
Name: es-query-builder
Version: 0.2.1
Summary: Pythaon package to make building queries easier
Home-page: https://github.com/rvr93/es_query_builder
Author: Vamsidhar Reddy Rajula
Author-email: r.vamsireddy93@gmail.com
License: MIT license
Keywords: es_query_builder
Classifier: Development Status :: 2 - Pre-Alpha
Classifier: Intended Audience :: Developers
Classifier: License :: OSI Approved :: MIT License
Classifier: Natural Language :: English
Classifier: Programming Language :: Python :: 3
Classifier: Programming Language :: Python :: 3.6
Classifier: Programming Language :: Python :: 3.7
Classifier: Programming Language :: Python :: 3.8
Requires-Python: >=3.6
License-File: LICENSE
License-File: AUTHORS.rst
